README.rst
setup.cfg
setup.py
docs/HISTORY.rst
docs/LICENSE.GPL
docs/LICENSE.txt
docs/MANUAL.txt
docs/screen.png
raptus/__init__.py
raptus.article.imageslider.egg-info/PKG-INFO
raptus.article.imageslider.egg-info/SOURCES.txt
raptus.article.imageslider.egg-info/dependency_links.txt
raptus.article.imageslider.egg-info/entry_points.txt
raptus.article.imageslider.egg-info/namespace_packages.txt
raptus.article.imageslider.egg-info/not-zip-safe
raptus.article.imageslider.egg-info/requires.txt
raptus.article.imageslider.egg-info/top_level.txt
raptus/article/__init__.py
raptus/article/imageslider/__init__.py
raptus/article/imageslider/configure.zcml
raptus/article/imageslider/browser/__init__.py
raptus/article/imageslider/browser/configure.zcml
raptus/article/imageslider/browser/slider-teaser.gif
raptus/article/imageslider/browser/slider.js
raptus/article/imageslider/browser/slider.pt
raptus/article/imageslider/browser/slider.py
raptus/article/imageslider/profiles/default/cssregistry.xml
raptus/article/imageslider/profiles/default/jsregistry.xml
raptus/article/imageslider/profiles/default/metadata.xml
raptus/article/imageslider/profiles/default/propertiestool.xml
raptus/article/imageslider/profiles/default/skins.xml
raptus/article/imageslider/profiles/default/viewlets.xml
raptus/article/imageslider/skins/raptus_article_imageslider/raptus.article.imageslider.css.dtml