Metadata-Version: 1.1
Name: raptus.article.imageslider
Version: 0.3
Summary: Provides components for showing images in jquerytools scrollable carousels.
Home-page: https://github.com/webmeisterei/raptus.article.imageslider
Author: Harald Friessnegger
Author-email: harald (at) webmeisterei dot com
License: GPL
Platform: UNKNOWN
Classifier: Programming Language :: Python
Classifier: Framework :: Plone
Classifier: Framework :: Plone :: 4.1
Classifier: Framework :: Plone :: 4.2
Classifier: Framework :: Plone :: 4.3
